test_train_validation_split_by_rajeev/split_train_validation.py
Test_train_validation_split-1.0.0.dist-info/LICENSE.txt
Test_train_validation_split-1.0.0.dist-info/METADATA
Test_train_validation_split-1.0.0.dist-info/WHEEL
Test_train_validation_split-1.0.0.dist-info/entry_points.txt
Test_train_validation_split-1.0.0.dist-info/top_level.txt
Test_train_validation_split-1.0.0.dist-info/RECORD
